sqaod/__init__.py
sqaod/common/__init__.py
sqaod/common/bipartite_graph_annealer_base.py
sqaod/common/bipartite_graph_bf_searcher_base.py
sqaod/common/checkers.py
sqaod/common/common.py
sqaod/common/cuda_probe.py
sqaod/common/dense_graph_annealer_base.py
sqaod/common/dense_graph_bf_searcher_base.py
sqaod/common/docstring.py
sqaod/common/envcheck.py
sqaod/common/formulas_base.py
sqaod/common/preference.py
sqaod/common/solver.py
sqaod/common/summary.py
sqaod/common/version.py
sqaod/cpu/__init__.py
sqaod/cpu/bipartite_graph_annealer.py
sqaod/cpu/bipartite_graph_bf_searcher.py
sqaod/cpu/cpu_bg_annealer.cpython-35m-x86_64-linux-gnu.so
sqaod/cpu/cpu_bg_bf_searcher.cpython-35m-x86_64-linux-gnu.so
sqaod/cpu/cpu_dg_annealer.cpython-35m-x86_64-linux-gnu.so
sqaod/cpu/cpu_dg_bf_searcher.cpython-35m-x86_64-linux-gnu.so
sqaod/cpu/cpu_formulas.cpython-35m-x86_64-linux-gnu.so
sqaod/cpu/dense_graph_annealer.py
sqaod/cpu/dense_graph_bf_searcher.py
sqaod/cpu/formulas.py
sqaod/cuda/__init__.py
sqaod/cuda/bipartite_graph_annealer.py
sqaod/cuda/bipartite_graph_bf_searcher.py
sqaod/cuda/cuda_bg_annealer.cpython-35m-x86_64-linux-gnu.so
sqaod/cuda/cuda_bg_bf_searcher.cpython-35m-x86_64-linux-gnu.so
sqaod/cuda/cuda_device.cpython-35m-x86_64-linux-gnu.so
sqaod/cuda/cuda_dg_annealer.cpython-35m-x86_64-linux-gnu.so
sqaod/cuda/cuda_dg_bf_searcher.cpython-35m-x86_64-linux-gnu.so
sqaod/cuda/cuda_formulas.cpython-35m-x86_64-linux-gnu.so
sqaod/cuda/dense_graph_annealer.py
sqaod/cuda/dense_graph_bf_searcher.py
sqaod/cuda/device.py
sqaod/cuda/formulas.py
sqaod/py/__init__.py
sqaod/py/bipartite_graph_annealer.py
sqaod/py/bipartite_graph_bf_searcher.py
sqaod/py/dense_graph_annealer.py
sqaod/py/dense_graph_bf_searcher.py
sqaod/py/formulas.py
sqaod/wildqat/__init__.py
sqaod/wildqat/opt.py
sqaod-1.0.2.dist-info/METADATA
sqaod-1.0.2.dist-info/WHEEL
sqaod-1.0.2.dist-info/top_level.txt
sqaod-1.0.2.dist-info/RECORD
