Metadata-Version: 1.2
Name: sqaod
Version: 1.0.2
Summary: A collection of solvers for simulated quantum annealing.
Home-page: https://github.com/shinmorino/sqaod/
Author: Shinya Morino
Author-email: shin.morino@gmail.com
Maintainer: Shinya Morino
Maintainer-email: shin.morino@gmail.com
License: UNKNOWN
Keywords: Simulated quantum annealing,Quantum annealing,Quantum computing,Monte Carlo,OpenMP,GPU,CUDA
Platform: UNKNOWN
Classifier: Operating System :: POSIX :: Linux
Classifier: Natural Language :: English
Classifier: License :: OSI Approved :: Apache Software License
Classifier: License :: OSI Approved :: Mozilla Public License 2.0 (MPL 2.0)
Classifier: License :: OSI Approved :: BSD License
Classifier: Topic :: Scientific/Engineering
Classifier: Topic :: Scientific/Engineering :: Artificial Intelligence
Classifier: Topic :: Scientific/Engineering :: Information Analysis
Classifier: Programming Language :: Python :: 2
Classifier: Programming Language :: Python :: 2.7
Classifier: Programming Language :: Python :: 3
Classifier: Programming Language :: Python :: 3.3
Classifier: Programming Language :: Python :: 3.4
Classifier: Programming Language :: Python :: 3.5
Classifier: Programming Language :: Python :: 3.6
Classifier: Programming Language :: Python :: 3.7
